.gitignore
CHANGES.txt
MANIFEST.in
README.rst
bootstrap.py
buildout.cfg
collective.linguadomains-configure.zcml
jenkins.cfg
setup.py
collective/__init__.py
collective.linguadomains.egg-info/PKG-INFO
collective.linguadomains.egg-info/SOURCES.txt
collective.linguadomains.egg-info/dependency_links.txt
collective.linguadomains.egg-info/entry_points.txt
collective.linguadomains.egg-info/namespace_packages.txt
collective.linguadomains.egg-info/not-zip-safe
collective.linguadomains.egg-info/requires.txt
collective.linguadomains.egg-info/top_level.txt
collective/linguadomains/__init__.py
collective/linguadomains/configure.zcml
collective/linguadomains/controller.py
collective/linguadomains/controlpanel.py
collective/linguadomains/interfaces.py
collective/linguadomains/rebuild_i18n.sh
collective/linguadomains/testing.py
collective/linguadomains/validator.py
collective/linguadomains/locales/collective.linguadomains.pot
collective/linguadomains/locales/en/LC_MESSAGES/collective.linguadomains.po
collective/linguadomains/locales/fr/LC_MESSAGES/collective.linguadomains.po
collective/linguadomains/profiles/default/controlpanel.xml
collective/linguadomains/profiles/default/metadata.xml
collective/linguadomains/profiles/default/registry.xml
collective/linguadomains/tests/__init__.py
collective/linguadomains/tests/base.py
collective/linguadomains/tests/test_integration_setup.py
collective/linguadomains/tests/test_integration_validator.py
collective/linguadomains/tests/test_unit_controller.py
collective/linguadomains/tests/test_unit_validator.py
collective/linguadomains/tests/utils.py
collective/linguadomains/upgrades/__init__.py
collective/linguadomains/upgrades/configure.zcml
collective/linguadomains/upgrades/v1000_to_1001.py