Metadata-Version: 1.0
Name: collective.linguadomains
Version: 1.1
Summary: Manage translated domains for Plone
Home-page: https://github.com/toutpt/collective.linguadomains
Author: JeanMichel FRANCOIS aka toutpt
Author-email: toutpt@gmail.com
License: GPL
Keywords: plone multilanguages linguaplone multidomains
Platform: UNKNOWN
Classifier: Programming Language :: Python
Classifier: Framework :: Plone
Classifier: Framework :: Plone :: 4.0
Classifier: Framework :: Plone :: 4.1
Classifier: Framework :: Plone :: 4.2
